mujoco_client/__init__.py
mujoco_client/main.py
mujoco_client-0.4.1.dist-info/METADATA
mujoco_client-0.4.1.dist-info/WHEEL
mujoco_client-0.4.1.dist-info/entry_points.txt
mujoco_client-0.4.1.dist-info/RECORD
