Metadata-Version: 2.4
Name: mujoco-client
Version: 0.4.1
Summary: Dora Node client for mujoco simulated robots.
License: MIT
Author: Hennzau
Author-email: <dev@enzo-le-van.fr>
Requires-Python: >=3.9
Classifier: License :: OSI Approved :: MIT License
Classifier: Programming Language :: Python :: 3
Classifier: Programming Language :: Python :: 3.9
Classifier: Programming Language :: Python :: 3.10
Classifier: Programming Language :: Python :: 3.11
Classifier: Programming Language :: Python :: 3.12
Classifier: Programming Language :: Python :: 3.13
Classifier: Programming Language :: Python :: 3.14
Requires-Dist: PyOpenGL (>=3.1.1a1,<3.2.0)
Requires-Dist: dora-rs (==0.3.5)
Requires-Dist: mujoco (>=3.1.6,<3.2.0)
